named_env/__init__.py
named_env/exceptions.py
named_env/namespace.py
named_env/py.typed
named_env/variables.py
named_env/version.py
named_env-2.4.1.dist-info/LICENSE
named_env-2.4.1.dist-info/METADATA
named_env-2.4.1.dist-info/WHEEL
named_env-2.4.1.dist-info/RECORD
